{
  "updated": "2026년 4월 24일 AM 02:15",
  "count": 8,
  "articles": [
    {
      "category": "industry",
      "title": "AI와 함께하는 디자인, 정신을 잃지 않기",
      "summary": "AI 협업자 Thia를 통해 실시간으로 디자인 아이디어를 발전시키는 방법을 소개한다. 비전과 음성 기능을 활용하여 초기 아이디어를 유지하고, 사고 과정을 개인적으로 관리할 수 있다.",
      "summary_full": "AI 협업자 Thia를 구축하여 디자인 과정에서 비전과 음성 기능을 활용하는 방법을 설명한다. 이를 통해 초기 아이디어를 원형 그대로 유지하고, 사고의 흐름을 개인적으로 관리할 수 있다. AI와 함께 화이트보드에서 스케치하며 창의적인 과정을 진행하는 경험을 공유한다. 이러한 방식은 자신의 행동 변화를 인식하는 데 도움을 줄 수 있다.",
      "keywords": [
        "AI 협업자",
        "디자인",
        "창의성"
      ],
      "source": "uxdesign.cc",
      "date": "4월 23일",
      "url": "https://uxdesign.cc/designing-with-ai-without-losing-your-mind-0cfba48f6309?source=rss----138adf9c44c---4"
    },
    {
      "category": "industry",
      "title": "메타, AI 투자 위해 8,000명 감원",
      "summary": "메타는 5월 20일부터 약 8,000명의 직원을 감원하고, 6,000개의 공석을 취소하며, 2026년 하반기 추가 감원을 계획하고 있다.",
      "summary_full": "메타는 전체 직원의 10%에 해당하는 약 8,000명을 감원하고, 6,000개의 공석을 취소하며, 2026년 하반기에 추가 감원을 계획하고 있다. 이번 감원은 성과 기반이 아닌 구조적 조정으로, 팀을 AI 중심의 '포드'로 재편성하고 있다. 메타는 AI 인프라에 1,150억에서 1,350억 달러를 투자할 예정이다. 생존자들에게는 후임자를 교육할 것을 요청하고 있다.",
      "keywords": [
        "메타",
        "AI",
        "감원"
      ],
      "source": "thenextweb.com",
      "date": "4월 23일",
      "url": "https://thenextweb.com/news/meta-layoffs-8000-ai-restructuring-may-2026"
    },
    {
      "category": "design",
      "title": "UX 디자이너의 악몽: '생산 준비 완료'가 디자인 산출물이 될 때",
      "summary": "UX 디자이너의 도구가 급격히 변화했으며, 시장의 요구에 의해 '디자이너는 코딩을 해야 하는가?'라는 논쟁이 종결되었다. 현재 UX 역할은 AI 보강 개발 및 기술 조정 능력을 점점 더 요구하고 있다.",
      "summary_full": "2026년 초, UX 디자이너의 도구가 갑자기 변화하는 모습을 보였다. '디자이너는 코딩을 해야 하는가?'라는 논쟁은 업계의 요구에 의해 강제로 결론이 나게 되었다. 현재 LinkedIn을 살펴보면 UX 역할에서 AI 보강 개발 및 기술 조정 능력이 점점 더 요구되고 있음을 알 수 있다. 이는 디자이너들이 기술적 능력을 갖추어야 한다는 압박을 증가시키고 있다.",
      "keywords": [
        "UX 디자인",
        "AI 보강 개발",
        "기술 조정"
      ],
      "source": "smashingmagazine.com",
      "date": "4월 22일",
      "url": "https://smashingmagazine.com/2026/04/production-ready-becomes-design-deliverable-ux/"
    },
    {
      "category": "design",
      "title": "좋은 디자이너, 나쁜 웹사이트: 제안",
      "summary": "접근성은 웹사이트 제작에서 가장 중요한 요소이다. 이 글은 디자이너들이 웹사이트의 접근성을 개선하기 위한 과제를 제시한다.",
      "summary_full": "접근성은 웹사이트 제작에서 가장 중요한 요소로, 이 글은 디자이너들이 이를 고려해야 한다고 강조한다. 다른 A List Apart 기사들은 혁신과 통찰을 제공하지만, 이 글은 독자들에게 실질적인 과제를 제시한다. 저자는 디자이너들이 좋은 사람이라는 점에 동의할 것이라고 말하며, 이 주제를 시작한다. 개인적인 의견이지만, 접근성을 개선하는 것이 중요하다는 메시지를 전달하고 있다.",
      "keywords": [
        "접근성",
        "웹사이트",
        "디자인"
      ],
      "source": "alistapart.com",
      "date": "4월 23일",
      "url": "https://alistapart.com/article/good-designers-bad-websites-a-proposal/"
    },
    {
      "category": "trend",
      "title": "미국 특수부대 병사, 마두로 습격에 대한 폴리마켓 베팅으로 체포",
      "summary": "한 중사급 군인이 베네수엘라 대통령 니콜라스 마두로의 체포에 대한 정보를 이용해 이익을 취한 혐의로 체포되었다. 이는 예측 시장에서 내부자 거래로 체포된 첫 번째 사례이다.",
      "summary_full": "미국의 한 중사급 군인이 베네수엘라 대통령 니콜라스 마두로의 체포에 대한 기밀 정보를 이용해 폴리마켓에서 베팅을 하여 이익을 취한 혐의로 체포되었다. 이 사건은 예측 시장에서 내부자 거래로 체포된 첫 번째 사례로 기록되었다. 군인은 기밀 정보를 이용해 불법적으로 수익을 얻은 것으로 보인다. 이 사건은 군 내부의 윤리와 법적 문제를 다시 한번 부각시키고 있다.",
      "keywords": [
        "특수부대",
        "마두로",
        "내부자 거래"
      ],
      "source": "wired.com",
      "date": "4월 23일",
      "url": "https://www.wired.com/story/us-special-forces-soldier-allegedly-profited-off-of-maduro-capture-on-polymarket/"
    },
    {
      "category": "trend",
      "title": "가장 위험한 대기업 디자이너는 배포할 수 있는 사람이다",
      "summary": "대기업에서는 역할 정의가 명확했지만, 이제는 디자이너가 배포할 수 있는 능력이 중요해졌다.",
      "summary_full": "과거 대기업에서는 디자이너, 엔지니어, PM, 연구자 각각의 역할이 명확하게 구분되었다. 그러나 이러한 경직된 구조는 비효율을 초래하고, '그건 내 일이 아니다'라는 말이 자주 들렸다. 현재는 디자이너가 실제로 제품을 배포할 수 있는 능력이 가장 중요하게 여겨진다. 이는 팀워크와 협업의 중요성을 강조한다.",
      "keywords": [
        "디자인",
        "협업",
        "대기업"
      ],
      "source": "dev.to",
      "date": "4월 23일",
      "url": "https://dev.to/ling_zhou_cdd0792b313758c/the-most-dangerous-designer-at-a-big-company-is-the-one-who-can-ship-69b"
    },
    {
      "category": "frontend",
      "title": "애플의 비전 프로 애니메이션을 CSS로 재현하기",
      "summary": "애플의 제품 애니메이션은 항상 영감을 주지만, 주로 자바스크립트와 다른 기술을 사용해왔다. 최근 CSS의 스크롤 애니메이션 기능을 활용해 이를 재구성할 수 있을지 고민해보았다.",
      "summary_full": "애플의 제품 애니메이션, 특히 스크롤링 테어다운은 항상 영감을 주는 요소였다. 이러한 최첨단 애니메이션은 주로 자바스크립트와 다른 기술을 사용해왔으며, 항상 반응형이 아니었다. 최근 CSS의 스크롤 애니메이션 기능이 발전하면서 이를 활용해 애니메이션을 재구성할 수 있을지에 대한 고민이 생겼다. 애플은 특정 너비에서 정적 이미지로 전환하기도 한다.",
      "keywords": [
        "애플",
        "CSS",
        "애니메이션"
      ],
      "source": "css-tricks.com",
      "date": "4월 23일",
      "url": "https://css-tricks.com/recreating-apples-vision-pro-animation-in-css/"
    },
    {
      "category": "frontend",
      "title": "암호화폐를 벌어들이는 자율 AI 에이전트 구축: 2026 기술 가이드",
      "summary": "2026년에는 블록체인 네트워크와 자율적으로 상호작용하며 암호화폐를 벌어들이는 AI 에이전트가 등장하고 있다. 이 글에서는 이러한 에이전트를 구축하는 과정에서 얻은 경험을 공유한다.",
      "summary_full": "2026년에는 블록체인 네트워크와 자율적으로 상호작용하며 보상을 받고 암호화폐를 벌어들이는 AI 에이전트의 흥미로운 융합이 이루어지고 있다. 필자는 이러한 에이전트를 구축하면서 배운 내용을 공유하고 있다. 이 에이전트의 아키텍처 개요와 작동 방식에 대한 설명이 포함될 예정이다. 자율 AI 에이전트는 다양한 작업을 수행하고, 보상을 받을 수 있는 잠재력을 가지고 있다.",
      "keywords": [
        "자율 AI 에이전트",
        "암호화폐",
        "블록체인 네트워크"
      ],
      "source": "dev.to",
      "date": "4월 24일",
      "url": "https://dev.to/writ_sop_525475eb063dc209/building-autonomous-ai-agents-that-earn-crypto-a-2026-technical-guide-3lnj"
    }
  ]
}